zhinst/comms_schemas/__init__.py
zhinst/comms_schemas/_version.py
zhinst/comms_schemas/py.typed
zhinst/comms_schemas/labone/__init__.py
zhinst/comms_schemas/labone/errors.py
zhinst/comms_schemas/labone/hpk_schema.py
zhinst/comms_schemas/labone/core/__init__.py
zhinst/comms_schemas/labone/core/errors.py
zhinst/comms_schemas/labone/core/helper.py
zhinst/comms_schemas/labone/core/kernel_session.py
zhinst/comms_schemas/labone/core/session.py
zhinst/comms_schemas/labone/core/subscription.py
zhinst/comms_schemas/labone/core/value.py
zhinst/comms_schemas/labone/mock/__init__.py
zhinst/comms_schemas/labone/mock/automatic_server.py
zhinst/comms_schemas/labone/mock/errors.py
zhinst/comms_schemas/labone/mock/session.py
zhinst/comms_schemas/labone/nodetree/__init__.py
zhinst/comms_schemas/labone/nodetree/entry_point.py
zhinst/comms_schemas/labone/nodetree/errors.py
zhinst/comms_schemas/labone/nodetree/helper.py
zhinst/comms_schemas/labone/nodetree/node.py
zhinst/comms_schemas/labone/nodetree/node_enum.py
zhinst/comms_schemas/labone/nodetree/node_info.py
zhinst_comms_schemas-4.0.0.dist-info/METADATA
zhinst_comms_schemas-4.0.0.dist-info/WHEEL
zhinst_comms_schemas-4.0.0.dist-info/licenses/LICENSE
zhinst_comms_schemas-4.0.0.dist-info/RECORD
