Metadata-Version: 2.4
Name: zhinst-comms_schemas
Version: 4.0.0
Summary: Server Schemas and Helper functions for the zhinst.comms package.
Project-URL: homepage, https://zhinst.com
Author-email: Zurich Instruments Development Team <info@zhinst.com>
License: Apache 2.0
License-File: LICENSE
Keywords: zhinst
Classifier: Development Status :: 5 - Production/Stable
Classifier: Intended Audience :: Developers
Classifier: Intended Audience :: Science/Research
Classifier: License :: OSI Approved :: Apache Software License
Classifier: Operating System :: OS Independent
Classifier: Programming Language :: Python :: 3.10
Classifier: Programming Language :: Python :: 3.11
Classifier: Programming Language :: Python :: 3.12
Classifier: Programming Language :: Python :: 3.13
Classifier: Topic :: Scientific/Engineering
Requires-Python: >=3.10
Requires-Dist: numpy>=1.20
Requires-Dist: packaging
Requires-Dist: typing-extensions>=4.8.0
Requires-Dist: zhinst-comms~=3.0
